geodeapp_back/__init__.py
geodeapp_back/app.py
tests/__init__.py
tests/conftest.py
tests/test_routes.py
geodeapp_back-0.4.1.dist-info/LICENSE
geodeapp_back-0.4.1.dist-info/METADATA
geodeapp_back-0.4.1.dist-info/WHEEL
geodeapp_back-0.4.1.dist-info/entry_points.txt
geodeapp_back-0.4.1.dist-info/top_level.txt
geodeapp_back-0.4.1.dist-info/RECORD
