Metadata-Version: 2.1
Name: geodeapp_back
Version: 0.4.1
Author-email: Geode-solutions <team-web@geode-solutions.com>
Project-URL: Homepage, https://github.com/Geode-solutions/geodeapp-back
Project-URL: Bug Tracker, https://github.com/Geode-solutions/geodeapp-back/issues
Classifier: Programming Language :: Python :: 3
Classifier: License :: OSI Approved :: MIT License
Classifier: Operating System :: OS Independent
Requires-Python: >=3.8
License-File: LICENSE
Requires-Dist: asgiref ==3.8.1
Requires-Dist: attrs ==24.2.0
Requires-Dist: blinker ==1.8.2
Requires-Dist: click ==8.1.7
Requires-Dist: colorama ==0.4.6
Requires-Dist: flask[async] ==3.0.3
Requires-Dist: flask-cors ==5.0.0
Requires-Dist: geode-background ==8.6.1
Requires-Dist: geode-common ==33.0.4
Requires-Dist: geode-conversion ==6.0.10
Requires-Dist: geode-explicit ==6.1.9
Requires-Dist: geode-implicit ==3.2.4
Requires-Dist: geode-numerics ==5.1.3
Requires-Dist: geode-simplex ==8.2.10
Requires-Dist: geode-viewables ==3.0.5
Requires-Dist: itsdangerous ==2.2.0
Requires-Dist: jinja2 ==3.1.4
Requires-Dist: jsonschema ==4.23.0
Requires-Dist: jsonschema-specifications ==2024.10.1
Requires-Dist: markupsafe ==3.0.1
Requires-Dist: opengeode-core ==15.5.0
Requires-Dist: opengeode-geosciences ==8.1.0
Requires-Dist: opengeode-geosciencesio ==5.2.1
Requires-Dist: opengeode-inspector ==6.1.4
Requires-Dist: opengeode-io ==7.0.3
Requires-Dist: opengeodeweb-back ==5.3.1
Requires-Dist: referencing ==0.35.1
Requires-Dist: rpds-py ==0.20.0
Requires-Dist: typing-extensions ==4.12.2
Requires-Dist: werkzeug ==3.0.4
